<annotation>
	<folder>photo_2_1</folder>
	<filename>27_000008.jpg</filename>
	<path>F:\Code\OpenCv_Python\Improve\NanoDet_Face\Images\photo_2_1\27.jpg</path>
	<source>
		<database>Unknown</database>
	</source>
	<size>
		<width>640</width>
		<height>512</height>
		<depth>1</depth>
	</size>
	<segmented>0</segmented>
	<object>
		<name>face</name>
		<pose>Unspecified</pose>
		<truncated>1</truncated>
		<difficult>0</difficult>
		<bndbox>
			<xmin>444</xmin>
			<ymin>68</ymin>
			<xmax>601</xmax>
			<ymax>254</ymax>
		</bndbox>
	</object>
	<object>
		<name>face</name>
		<pose>Unspecified</pose>
		<truncated>0</truncated>
		<difficult>0</difficult>
		<bndbox>
			<xmin>211</xmin>
			<ymin>121</ymin>
			<xmax>316</xmax>
			<ymax>244</ymax>
		</bndbox>
	</object>
</annotation>