<annotation>
	<folder>photo_2_1</folder>
	<filename>70_000008.jpg</filename>
	<path>F:\Code\OpenCv_Python\Improve\NanoDet_Face\Images\photo_2_1\70.jpg</path>
	<source>
		<database>Unknown</database>
	</source>
	<size>
		<width>640</width>
		<height>512</height>
		<depth>1</depth>
	</size>
	<segmented>0</segmented>
	<object>
		<name>face</name>
		<pose>Unspecified</pose>
		<truncated>0</truncated>
		<difficult>0</difficult>
		<bndbox>
			<xmin>62</xmin>
			<ymin>243</ymin>
			<xmax>150</xmax>
			<ymax>355</ymax>
		</bndbox>
	</object>
	<object>
		<name>face</name>
		<pose>Unspecified</pose>
		<truncated>0</truncated>
		<difficult>0</difficult>
		<bndbox>
			<xmin>323</xmin>
			<ymin>333</ymin>
			<xmax>424</xmax>
			<ymax>450</ymax>
		</bndbox>
	</object>
</annotation>